autobatch/__init__.py
autobatch/autobatch.py
autobatch-0.0.2.dist-info/LICENSE.txt
autobatch-0.0.2.dist-info/METADATA
autobatch-0.0.2.dist-info/WHEEL
autobatch-0.0.2.dist-info/top_level.txt
autobatch-0.0.2.dist-info/RECORD
