Metadata-Version: 2.1
Name: autobatch
Version: 0.0.2
Summary: auto batch process 
Home-page: https://github.com/Kaijien/autobatch
Author: kaijien xue
Author-email: chuang_xue@qq.com
License: UNKNOWN
Platform: UNKNOWN
Classifier: Programming Language :: Python :: 3
Classifier: License :: OSI Approved :: MIT License
Classifier: Operating System :: OS Independent
